rompy/__init__.py
rompy/data.py
rompy/derivatives.py
rompy/eim.py
rompy/fits.py
rompy/greedy.py
rompy/integrals.py
rompy/lib.py
rompy/multivar.py
rompy/surrogate.py
rompy/training.py
rompy/univar.py
forked_rompy-0.0.3.dist-info/METADATA
forked_rompy-0.0.3.dist-info/WHEEL
forked_rompy-0.0.3.dist-info/top_level.txt
forked_rompy-0.0.3.dist-info/RECORD
