Metadata-Version: 2.1
Name: forked-rompy
Version: 0.0.3
Summary: reduced order modelling
Home-page: https://github.com/Cyberface/rompy
Author: Chad Galley, Sebastian Khan
Author-email: KhanS22@Cardiff.ac.uk
License: UNKNOWN
Platform: UNKNOWN
Classifier: Programming Language :: Python :: 3
Requires-Python: >=3.6
